dkpy/__init__.py
dkpy/controller_synthesis.py
dkpy/d_scale_fit.py
dkpy/dk_iteration.py
dkpy/structured_singular_value.py
dkpy/utilities.py
dkpy-0.1.8.dist-info/METADATA
dkpy-0.1.8.dist-info/WHEEL
dkpy-0.1.8.dist-info/licenses/LICENSE
dkpy-0.1.8.dist-info/RECORD
