Metadata-Version: 2.4
Name: dkpy
Version: 0.1.8
Summary: D-K iteration in Python
Project-URL: Homepage, https://github.com/decargroup/dkpy
Project-URL: Issues, https://github.com/decargroup/dkpy/issues
Author-email: Steven Dahdah <steven.dahdah@mail.mcgill.ca>, James Richard Forbes <james.richard.forbes@mcgill.ca>
License: MIT License
License-File: LICENSE
Classifier: License :: OSI Approved :: MIT License
Classifier: Operating System :: OS Independent
Classifier: Programming Language :: Python :: 3
Requires-Python: <3.14,>=3.7
Requires-Dist: control>=0.10.0
Requires-Dist: cvxpy>=1.5.0
Requires-Dist: joblib>=1.4.0
Requires-Dist: matplotlib>=3.9.0
Requires-Dist: numpy>=1.21.0
Requires-Dist: scipy>=1.7.0
Requires-Dist: slycot>=0.6.0
Provides-Extra: solvers
Requires-Dist: mosek>=9.2.49; extra == 'solvers'
